beakerx_all/__init__.py
beakerx_all/_version.py
beakerx_all-2.0.1.dist-info/METADATA
beakerx_all-2.0.1.dist-info/WHEEL
beakerx_all-2.0.1.dist-info/top_level.txt
beakerx_all-2.0.1.dist-info/RECORD
